lettergame/__init__.py
lettergame/game.py
lettergame-1.0.0.dist-info/METADATA
lettergame-1.0.0.dist-info/WHEEL
lettergame-1.0.0.dist-info/entry_points.txt
lettergame-1.0.0.dist-info/RECORD
