Metadata-Version: 2.4
Name: lettergame
Version: 1.0.0
Summary: Play a word-guessing game
Project-URL: Homepage, https://github.com/xorwow/lettergame
Project-URL: Issues, https://github.com/xorwow/lettergame/issues
Author-email: xorwow <pip@xorwow.de>
Classifier: License :: OSI Approved :: MIT License
Classifier: Operating System :: OS Independent
Classifier: Programming Language :: Python :: 3
Requires-Python: >=3.9
Requires-Dist: termcolor
